condom/__init__.py
condom/architecture.s.HTML
condom/module.MD
condom/module.s.HTML
condom/__agenda/maybes.s.HTML
condom/__agenda/priorities.s.HTML
condom/__agenda/processes/errout/script.py
condom/__agenda/processes/errout/start.py
condom/__agenda/processes/errout_v1/script.py
condom/__agenda/processes/errout_v1/start.py
condom/__agenda/processes/errout_v2/script.py
condom/__agenda/processes/errout_v2/start.py
condom/__license/license.s.HTML
condom/_book/advanced tutorial.s.HTML
condom/_book/book.s.HTML
condom/_book/example output.s.HTML
condom/_book/relevant.s.HTML
condom/_clique/__init__.py
condom/_clique/group/__init__.py
condom/_status/establish.py
condom/_status/status.proc.py
condom/_status/status.s.HTML
condom/_status/status_py.py
condom/_status/DB/records.json
condom/_status/monitors/-1_start/status_1.py
condom/_status/monitors/-1_start/chassis/modules/monitor_1.py
condom/_status/monitors/0_start/status_1.py
condom/_status/monitors/0_start/chassis/modules/monitor_1.py
condom/_status/monitors/1/status_1.py
condom/_status/monitors/1/stasis/path_1_health.py
condom/_status/monitors/1/stasis/path_2_health.py
condom/_status/monitors/2/status_1.py
condom/_status/monitors/2/stasis/1_health.py
condom/_status/monitors/2/stasis/2_health.py
condom/_status/monitors/2/stasis/modules/MODULE_1.py
condom/_status/monitors/3_empty_glob/status_1.py
condom/_status/monitors/4_bad_import/status_1.py
condom/_status/monitors/4_bad_import/stasis/1_health.py
condom/_status/monitors/5__file__/status_1.py
condom/_status/monitors/5__file__/stasis/1_health.py
condom/_status/monitors/5__file__/stasis/MODULES/MODULE_1.py
condom/_status/monitors/6_various/status_1.py
condom/_status/monitors/6_various/stasis/1_health.py
condom/_status/monitors/6_various/stasis/2_health.py
condom/_status/monitors/6_various/stasis/3_health.py
condom/_status/monitors/6_various/stasis/MODULES/MODULE_1.py
condom/_status/monitors/7/status_1.py
condom/_status/monitors/7/stasis/guarantee_1.py
condom-1.0.3.dist-info/METADATA
condom-1.0.3.dist-info/WHEEL
condom-1.0.3.dist-info/entry_points.txt
condom-1.0.3.dist-info/top_level.txt
condom-1.0.3.dist-info/RECORD
